odoo/addons/report_qweb_operating_unit/README.rst
odoo/addons/report_qweb_operating_unit/__init__.py
odoo/addons/report_qweb_operating_unit/__manifest__.py
odoo/addons/report_qweb_operating_unit/i18n/es_MX.po
odoo/addons/report_qweb_operating_unit/i18n/it.po
odoo/addons/report_qweb_operating_unit/i18n/report_qweb_operating_unit.pot
odoo/addons/report_qweb_operating_unit/models/__init__.py
odoo/addons/report_qweb_operating_unit/models/operating_unit.py
odoo/addons/report_qweb_operating_unit/readme/CONTRIBUTORS.md
odoo/addons/report_qweb_operating_unit/readme/DESCRIPTION.md
odoo/addons/report_qweb_operating_unit/static/description/icon.png
odoo/addons/report_qweb_operating_unit/static/description/index.html
odoo/addons/report_qweb_operating_unit/tests/__init__.py
odoo/addons/report_qweb_operating_unit/tests/test_report_qweb_operating_unit.py
odoo/addons/report_qweb_operating_unit/views/operating_unit_view.xml
odoo/addons/report_qweb_operating_unit/views/report_qweb_operating_unit.xml
odoo_addon_report_qweb_operating_unit-18.0.1.0.0.2.dist-info/METADATA
odoo_addon_report_qweb_operating_unit-18.0.1.0.0.2.dist-info/WHEEL
odoo_addon_report_qweb_operating_unit-18.0.1.0.0.2.dist-info/top_level.txt
odoo_addon_report_qweb_operating_unit-18.0.1.0.0.2.dist-info/RECORD
